{"type": "Feature", "id": 12515141, "properties": {"woe:id": 12515141, "woe:parent_id": 151960, "woe:name": "St. Eustatius Airport", "woe:placetype": 14, "woe:placetype_name": "Airport", "woe:lang": "ENG", "iso:country": "BQ", "meta:provider": ["geoplanet:7.3.1", "geoplanet:7.3.2", "geoplanet:7.4.0", "geoplanet:7.4.1", "geoplanet:7.5.1", "geoplanet:7.5.2", "geoplanet:7.6.0", "geoplanet:7.8.1", "geoplanet:7.9.0", "geoplanet:7.10.0", "geoplanet:8.0.0", "woeplanet:8.0.0"], "meta:indexed": "2020-08-20T20:57:43.006684", "woe:alias_ENG_V": ["EUX Airport", "EUX"], "meta:updated": "2020-08-22T02:59:15.490925", "woe:hierarchy": {"continent": 24865672, "country": 56558056, "town": 0, "planet": 1, "county": 0, "suburb": 0, "state": 24549809, "region": 0, "localadmin": 0}, "woe:timezone_id": 28350749, "woe:hash": "de55x424by1u", "woe:centroid": [-62.973598, 17.503099], "geom:latitude": 17.503099, "geom:longitude": -62.973598, "geom:hash": "de55x424by1u", "woe:latitude": 17.503099, "geom:centroid": [-62.973598, 17.503099], "woe:longitude": -62.973598, "woe:repo": "woeplanet-airport-bq"}, "geometry": {"coordinates": [-62.973598, 17.503099], "type": "Point"}}
